hawk_eyes/__init__.py
hawk_eyes/demo.py
hawk_eyes/face/__init__.py
hawk_eyes/face/src/__init__.py
hawk_eyes/face/src/aux_functions.py
hawk_eyes/face/src/face_align.py
hawk_eyes/face/src/face_detection.py
hawk_eyes/face/src/face_embedding.py
hawk_eyes/face/src/landmark.py
hawk_eyes/face/src/reference_world.py
hawk_eyes/ocr/__init__.py
hawk_eyes/tracking/__init__.py
hawk_eyes/tracking/src/__init__.py
hawk_eyes/tracking/src/basetrack.py
hawk_eyes/tracking/src/byte_tracker.py
hawk_eyes/tracking/src/kalman_filter.py
hawk_eyes/tracking/src/matching.py
hawk_eyes/yolov5/__init__.py
hawk_eyes/yolov5/src/__init__.py
hawk_eyes/yolov5/src/yolov5.py
hawk_eyes/yolov5/src/models/__init__.py
hawk_eyes/yolov5/src/models/common.py
hawk_eyes/yolov5/src/models/experimental.py
hawk_eyes/yolov5/src/models/tf.py
hawk_eyes/yolov5/src/models/yolo.py
hawk_eyes/yolov5/src/utils/__init__.py
hawk_eyes/yolov5/src/utils/activations.py
hawk_eyes/yolov5/src/utils/augmentations.py
hawk_eyes/yolov5/src/utils/autoanchor.py
hawk_eyes/yolov5/src/utils/autobatch.py
hawk_eyes/yolov5/src/utils/benchmarks.py
hawk_eyes/yolov5/src/utils/callbacks.py
hawk_eyes/yolov5/src/utils/dataloaders.py
hawk_eyes/yolov5/src/utils/downloads.py
hawk_eyes/yolov5/src/utils/general.py
hawk_eyes/yolov5/src/utils/loss.py
hawk_eyes/yolov5/src/utils/metrics.py
hawk_eyes/yolov5/src/utils/plots.py
hawk_eyes/yolov5/src/utils/torch_utils.py
hawk_eyes-2.1.2.dist-info/LICENSE
hawk_eyes-2.1.2.dist-info/METADATA
hawk_eyes-2.1.2.dist-info/WHEEL
hawk_eyes-2.1.2.dist-info/top_level.txt
hawk_eyes-2.1.2.dist-info/RECORD
