Metadata-Version: 2.1
Name: hawk-eyes
Version: 2.1.2
Summary: Face recognize, Object tracking, OCR
Home-page: https://github.com/Duy-NM/hawk_eye
Author: Duy Nguyen Manh
Author-email: manhduy160396@email.com
License: MIT License
License-File: LICENSE
Requires-Dist: gdown
Requires-Dist: onnxruntime-gpu (==1.10)
